pretiac/__init__.py
pretiac/check_executor.py
pretiac/cli.py
pretiac/client.py
pretiac/config.py
pretiac/exceptions.py
pretiac/log.py
pretiac/object_types.py
pretiac/py.typed
pretiac/raw_client.py
pretiac/request_handler.py
pretiac-0.4.0.dist-info/LICENSE.txt
pretiac-0.4.0.dist-info/METADATA
pretiac-0.4.0.dist-info/WHEEL
pretiac-0.4.0.dist-info/entry_points.txt
pretiac-0.4.0.dist-info/RECORD
